myapp/__init__.py
myapp/app2.py
myapp/__pycache__/__init__.cpython-312.pyc
myapp/__pycache__/app2.cpython-312.pyc
myapp_srinithya_12-1.0.0.dist-info/licenses/LICENSE
myapp_srinithya_12-1.0.0.dist-info/METADATA
myapp_srinithya_12-1.0.0.dist-info/WHEEL
myapp_srinithya_12-1.0.0.dist-info/entry_points.txt
myapp_srinithya_12-1.0.0.dist-info/top_level.txt
myapp_srinithya_12-1.0.0.dist-info/RECORD
