Metadata-Version: 2.4
Name: myapp-srinithya-12
Version: 1.0.0
Summary: My packaged Python application
Author-email: Srinithya <yeltisrinithyareddy@gmail.com>
License-Expression: MIT
Requires-Python: >=3.8
License-File: LICENSE
Requires-Dist: PyQt6>=6.5.0
Dynamic: license-file
